Metadata-Version: 1.1
Name: convert2php
Version: 0.0.1
Summary: A python script to convert simple php code to python
Home-page: https://github.com/danleyb2/php2python
Author: Nyaundi Brian
Author-email: ndieksman@gmail.com
License: MIT
Download-URL: https://github.com/danleyb2/php2python/tarball/0.0.1
Keywords: php,python,convert
Platform: any
Classifier: Environment :: Console
Classifier: Intended Audience :: Developers
Classifier: License :: OSI Approved :: MIT License
Classifier: Operating System :: OS Independent
Classifier: Programming Language :: Python
Classifier: Programming Language :: Python :: 2.7
